spacetraders_sdk/__init__.py
spacetraders_sdk/ratelimit.py
spacetraders_sdk/spacetraders_api.py
spacetraders_sdk/spacetraders_constants.py
spacetraders_sdk/spacetraders_enums.py
spacetraders_sdk/spacetraders_helper.py
spacetraders_sdk/spacetraders_logger.py
spacetraders_sdk/spacetraders_objects.py
spacetraders_sdk/spacetraders_sdk.py
spacetraders_sdk-2.3.1.8.dist-info/LICENSE
spacetraders_sdk-2.3.1.8.dist-info/METADATA
spacetraders_sdk-2.3.1.8.dist-info/WHEEL
spacetraders_sdk-2.3.1.8.dist-info/RECORD
